qsarmil/__init__.py
qsarmil/lazy.py
qsarmil/conformer/__init__.py
qsarmil/conformer/base.py
qsarmil/conformer/rdkit.py
qsarmil/descriptor/__init__.py
qsarmil/descriptor/rdkit.py
qsarmil/descriptor/wrapper.py
qsarmil/fragment/__init__.py
qsarmil/fragment/rdkit.py
qsarmil/utils/__init__.py
qsarmil/utils/logging.py
qsarmil-1.0.0.dist-info/licenses/LICENSE
qsarmil-1.0.0.dist-info/METADATA
qsarmil-1.0.0.dist-info/WHEEL
qsarmil-1.0.0.dist-info/top_level.txt
qsarmil-1.0.0.dist-info/RECORD
