Metadata-Version: 2.4
Name: qsarmil
Version: 1.0.0
Summary: Molecular multi-instance machine learning
Author-email: Dmitry Zankov <dvzankov@gmail.com>
License: MIT
License-File: LICENSE
Requires-Dist: mikit-learn
Requires-Dist: rdkit
Requires-Dist: molfeat
Requires-Dist: py3Dmol
Requires-Dist: tqdm
Requires-Dist: huggingface_hub
Dynamic: license-file
